obutills/__init__.py
obutills/config.py
obutills/files.py
obutills/logging.py
obutills/os.py
obutills-0.1.0.dist-info/METADATA
obutills-0.1.0.dist-info/WHEEL
obutills-0.1.0.dist-info/top_level.txt
obutills-0.1.0.dist-info/RECORD
