Metadata-Version: 2.4
Name: obutills
Version: 0.1.0
Summary: A collection of utility functions and tools for Python development
Home-page: https://github.com/orbical-dev/obutills
Author: Zachary Jones
Author-email: zacharyj@orbical.dev
Keywords: utils,tools,system,config,logging,files
Classifier: Programming Language :: Python :: 3
Classifier: License :: OSI Approved :: MIT License
Classifier: Operating System :: OS Independent
Classifier: Development Status :: 4 - Beta
Classifier: Intended Audience :: Developers
Classifier: Topic :: Software Development :: Libraries :: Python Modules
Requires-Python: >=3.6
Requires-Dist: pyyaml>=5.1
Dynamic: author
Dynamic: author-email
Dynamic: classifier
Dynamic: description
Dynamic: description-content-type
Dynamic: home-page
Dynamic: keywords
Dynamic: requires-dist
Dynamic: requires-python
Dynamic: summary
